affinidi_tdk_iam_client/__init__.py
affinidi_tdk_iam_client/api/__init__.py
affinidi_tdk_iam_client/api/authz_api.py
affinidi_tdk_iam_client/api/consumer_auth_api.py
affinidi_tdk_iam_client/api/default_api.py
affinidi_tdk_iam_client/api/policies_api.py
affinidi_tdk_iam_client/api/projects_api.py
affinidi_tdk_iam_client/api/sts_api.py
affinidi_tdk_iam_client/api/tokens_api.py
affinidi_tdk_iam_client/api/well_known_api.py
affinidi_tdk_iam_client/api_client.py
affinidi_tdk_iam_client/api_response.py
affinidi_tdk_iam_client/configuration.py
affinidi_tdk_iam_client/exceptions.py
affinidi_tdk_iam_client/models/__init__.py
affinidi_tdk_iam_client/models/action_forbidden_error.py
affinidi_tdk_iam_client/models/add_user_to_project_input.py
affinidi_tdk_iam_client/models/consumer_auth_token_endpoint_input.py
affinidi_tdk_iam_client/models/consumer_auth_token_endpoint_output.py
affinidi_tdk_iam_client/models/cors_consumer_auth_token_endpoint_ok.py
affinidi_tdk_iam_client/models/cors_grant_access_vfs_ok.py
affinidi_tdk_iam_client/models/cors_update_access_vfs_ok.py
affinidi_tdk_iam_client/models/create_project_input.py
affinidi_tdk_iam_client/models/create_project_scoped_token_input.py
affinidi_tdk_iam_client/models/create_project_scoped_token_output.py
affinidi_tdk_iam_client/models/create_token_input.py
affinidi_tdk_iam_client/models/delete_access_output.py
affinidi_tdk_iam_client/models/grant_access_input.py
affinidi_tdk_iam_client/models/grant_access_output.py
affinidi_tdk_iam_client/models/invalid_did_error.py
affinidi_tdk_iam_client/models/invalid_jwt_token_error.py
affinidi_tdk_iam_client/models/invalid_parameter_error.py
affinidi_tdk_iam_client/models/json_web_key_dto.py
affinidi_tdk_iam_client/models/json_web_key_set_dto.py
affinidi_tdk_iam_client/models/not_found_error.py
affinidi_tdk_iam_client/models/policy_dto.py
affinidi_tdk_iam_client/models/policy_statement_dto.py
affinidi_tdk_iam_client/models/principal_cannot_be_deleted_error.py
affinidi_tdk_iam_client-1.61.0.dist-info/METADATA
affinidi_tdk_iam_client-1.61.0.dist-info/WHEEL
affinidi_tdk_iam_client-1.61.0.dist-info/RECORD
